ls2d/__init__.py
ls2d/ecmwf/IFS_tools.py
ls2d/ecmwf/L137_grid.txt
ls2d/ecmwf/L60_grid.txt
ls2d/ecmwf/__init__.py
ls2d/ecmwf/download_cams.py
ls2d/ecmwf/download_era5.py
ls2d/ecmwf/era_tools.py
ls2d/ecmwf/patch_cds_ads.py
ls2d/ecmwf/read_cams.py
ls2d/ecmwf/read_era5.py
ls2d/ecmwf/read_era5_xr.py
ls2d/src/__init__.py
ls2d/src/finite_difference.py
ls2d/src/grid.py
ls2d/src/messages.py
ls2d/src/slurm.py
ls2d/src/spatial_tools.py
ls2d-1.0.13.dist-info/LICENSE.txt
ls2d-1.0.13.dist-info/METADATA
ls2d-1.0.13.dist-info/WHEEL
ls2d-1.0.13.dist-info/top_level.txt
ls2d-1.0.13.dist-info/RECORD
