Metadata-Version: 2.1
Name: ls2d
Version: 1.0.13
Summary: Python toolkit to downscale ERA5 with doubly-periodic large-eddy simulation
Author-email: Bart van Stratum <bart.vanstratum@wur.nl>
License: GNU GENERAL PUBLIC LICENSE
Project-URL: Homepage, https://github.com/LS2D/LS2D
Keywords: meteorology,ERA5,large-eddy simulation
Classifier: License :: OSI Approved :: GNU General Public License v3 (GPLv3)
Classifier: Programming Language :: Python
Classifier: Programming Language :: Python :: 3
Classifier: Operating System :: POSIX :: Linux
Classifier: Operating System :: MacOS
Requires-Python: >=3.6
License-File: LICENSE.txt
Requires-Dist: numpy
Requires-Dist: scipy
Requires-Dist: netCDF4
Requires-Dist: xarray
Requires-Dist: matplotlib
Requires-Dist: requests
Requires-Dist: dill
Requires-Dist: pyyaml
Requires-Dist: dask
Provides-Extra: cds
Requires-Dist: cdsapi; extra == "cds"
